reemweight/__init__.py
reemweight/data_examiner.py
reemweight/linear.py
reemweight/nonLinear.py
reemweight-0.4.dist-info/LICENCE.txt
reemweight-0.4.dist-info/METADATA
reemweight-0.4.dist-info/WHEEL
reemweight-0.4.dist-info/top_level.txt
reemweight-0.4.dist-info/RECORD
