Metadata-Version: 2.1
Name: reemweight
Version: 0.4
Summary: <The Python package is designed to assist with the initialization of weights in a neural network sequential model. The package uses machine learning algorithms (MLAs) to initialize the weights, which can lead to improved model performance. Additionally, the package provides a means to compare the results of this weight strategy with other weight initialization strategies.>
Author: Reem Almoshbb
Author-email: rsalmoshbb@gmail.com
Classifier: Programming Language :: Python :: 3
Classifier: License :: OSI Approved :: MIT License
Classifier: Operating System :: OS Independent
License-File: LICENCE.txt
